jtag_tap/tap.sv
/* verilator lint_off UNUSEDSIGNAL */

module tap (

    input   logic tck, // JTAG clock
    input   logic tdi,
    output  logic tdo,
    input   logic tms,
    input   logic trst

);

    state_machine::states_t current_state;

    logic [31:0] shift_reg_32;

    logic [31:0] baseline_register_idcode;
    logic [31:0] baseline_register_ir;

    initial begin
        $display("Hello World");
        $finish;
    end

    always_ff @(posedge tck)
    begin
        tdo <= 0;
    end

    always_ff @(posedge tck)
    begin

        if (trst == 1) begin

            baseline_register_idcode <= 32'h10e31913; // 0001 0000 1110 0011 0001 1001 0001 0011
            baseline_register_ir <= 32'hFFFFFFFF; // preselect the IDCODE baseline register on reset. This means shifting DR after a reset will produce the IDCODE of the target chip

            shift_reg_32 <= 32'h00;

            current_state <= state_machine::TEST_LOGIC_RESET;

        end else begin

            case (current_state)

                state_machine::TEST_LOGIC_RESET: begin // 0
                    if (tms == 0) begin
                        current_state <= state_machine::RUN_TEST_IDLE;
                    end
                end

                state_machine::RUN_TEST_IDLE: begin // 1
                    if (tms == 1) begin
                        current_state <= state_machine::SELECT_DR;
                    end
                end

                state_machine::SELECT_DR: begin // 2
                    if (tms == 0) begin
                        current_state <= state_machine::CAPTURE_DR;
                    end else begin
                        current_state <= state_machine::SELECT_IR; // 9
                    end
                end

                state_machine::CAPTURE_DR: begin // 3

                    // look at code in basline IR register
                    // copy baseline register identified by baseline IR content into shift register

                    // capture data into the correct shift register
                    case (baseline_register_ir)

                        // all ones is the identifier for the IDCODE register, which contains the unique ID of the chip so openocd can perform a comparison agains the code specified in the configuration file
                        // That way openocd is not used with the wrong configuration file on a targe-board
                        32'hFFFFFFFF: begin
                            shift_reg_32 <= baseline_register_idcode;
                        end

                        default: begin end
                    endcase

                    if (tms == 0) begin
                        current_state <= state_machine::SHIFT_DR;
                    end else begin
                        current_state <= state_machine::EXIT_1_DR;
                    end
                end

                state_machine::SHIFT_DR: begin // 4

                    // select the correct shift register to shift
                    case (baseline_register_ir)

                        32'hFFFFFFFF: begin // idcode selected
                            tdo <= shift_reg_32[0]; // icode is captured into 32 bit shift register
                            shift_reg_32 <= { tdi, shift_reg_32[31:1] };
                        end

                        default: begin end
                    endcase

                    if (tms == 1) begin
                        current_state <= state_machine::EXIT_1_DR;
                    end
                end

                state_machine::EXIT_1_DR: begin // 5
                    if (tms == 0) begin
                        current_state <= state_machine::PAUSE_DR;
                    end else begin
                        current_state <= state_machine::UPDATE_DR;
                    end
                end

                state_machine::PAUSE_DR: begin // 6
                    if (tms == 1) begin
                        current_state <= state_machine::EXIT_2_DR;
                    end
                end

                state_machine::EXIT_2_DR: begin // 7
                    if (tms == 0) begin
                        current_state <= state_machine::SHIFT_DR;
                    end else begin
                        current_state <= state_machine::UPDATE_DR;
                    end
                end

                state_machine::UPDATE_DR: begin // 8
                    if (tms == 0) begin
                        current_state <= state_machine::RUN_TEST_IDLE;
                    end else begin
                        current_state <= state_machine::SELECT_DR;
                    end
                end

                state_machine::SELECT_IR: begin // 9
                    if (tms == 0) begin
                        current_state <= state_machine::CAPTURE_IR;
                    end else begin
                        current_state <= state_machine::TEST_LOGIC_RESET;
                    end
                end

                state_machine::CAPTURE_IR: begin // 10
                    if (tms == 0) begin
                        current_state <= state_machine::SHIFT_IR;
                    end else begin
                        current_state <= state_machine::EXIT_1_IR;
                    end
                end

                state_machine::SHIFT_IR: begin // 11



                    if (tms == 1) begin
                        current_state <= state_machine::EXIT_1_IR;
                    end
                end

                state_machine::EXIT_1_IR: begin // 12
                    if (tms == 0) begin
                        current_state <= state_machine::PAUSE_IR;
                    end else begin
                        current_state <= state_machine::UPDATE_IR;
                    end
                end

                state_machine::PAUSE_IR: begin // 13
                    if (tms == 1) begin
                        current_state <= state_machine::EXIT_2_IR;
                    end
                end

                state_machine::EXIT_2_IR: begin // 14
                    if (tms == 0) begin
                        current_state <= state_machine::SHIFT_IR;
                    end else begin
                        current_state <= state_machine::UPDATE_IR;
                    end
                end

                state_machine::UPDATE_IR: begin // 15
                    if (tms == 0) begin
                        current_state <= state_machine::RUN_TEST_IDLE;
                    end else begin
                        current_state <= state_machine::SELECT_DR;
                    end
                end

                default: begin end

            endcase

        end

    end

endmodule;

/* verilator lint_on UNUSEDSIGNAL */

jtag_tap/waveform.vcd
$version Generated by VerilatedVcd $end
$timescale 1ps $end
 $scope module TOP $end
  $var wire 1 ' tck $end
  $var wire 1 ( tdi $end
  $var wire 1 ) tdo $end
  $var wire 1 * tms $end
  $var wire 1 + trst $end
  $scope module tap $end
   $var wire 1 ' tck $end
   $var wire 1 ( tdi $end
   $var wire 1 ) tdo $end
   $var wire 1 * tms $end
   $var wire 1 + trst $end
   $var wire 4 # current_state [3:0] $end
   $var wire 32 $ shift_reg_32 [31:0] $end
   $var wire 32 % baseline_register_idcode [31:0] $end
   $var wire 32 & baseline_register_ir [31:0] $end
  $upscope $end
 $upscope $end
$enddefinitions $end


#0
b0000 #
b00000000000000000000000000000000 $
b00000000000000000000000000000000 %
b00000000000000000000000000000000 &
1'
0(
0)
0*
1+
#1
0'
#2
b00010000111000110001100100010011 %
b11111111111111111111111111111111 &
1'
#3
0'
#4
1'
#5
0'
#6
1'
#7
0'
#8
1'
#9
0'
#10
1'
1*
0+
#11
0'
#12
1'
#13
0'
#14
1'
#15
0'
#16
1'
#17
0'
#18
1'
#19
0'
#20
0*
#30
1*
#31
1'
#32
0'
#33
1'
#34
0'
#35
1'
#36
0'
#37
0*
#38
b0001 #
1'
#39
0'
#40
1*
#41
b0010 #
1'
#42
0'
#43
0*
#44
b0011 #
1'
#45
0'
#46
b0100 #
b00010000111000110001100100010011 $
1'
#47
0'
#48
b10001000011100011000110010001001 $
1'
1(
1)
#49
0'
#50
b11000100001110001100011001000100 $
1'
#51
0'
#52
b11100010000111000110001100100010 $
1'
0)
#53
0'
#54
b11110001000011100011000110010001 $
1'
#55
0'
#56
b11111000100001110001100011001000 $
1'
1)
#57
0'
#58
b11111100010000111000110001100100 $
1'
0)
#59
0'
#60
b11111110001000011100011000110010 $
1'
#61
0'
#62
b11111111000100001110001100011001 $
1'
#63
0'
#64
b11111111100010000111000110001100 $
1'
1)
#65
0'
#66
b11111111110001000011100011000110 $
1'
0)
#67
0'
#68
b11111111111000100001110001100011 $
1'
#69
0'
#70
b11111111111100010000111000110001 $
1'
1)
#71
0'
#72
b11111111111110001000011100011000 $
1'
#73
0'
#74
b11111111111111000100001110001100 $
1'
0)
#75
0'
#76
b11111111111111100010000111000110 $
1'
#77
0'
#78
b11111111111111110001000011100011 $
1'
#79
0'
#80
b11111111111111111000100001110001 $
1'
1)
#81
0'
#82
b11111111111111111100010000111000 $
1'
#83
0'
#84
b11111111111111111110001000011100 $
1'
0)
#85
0'
#86
b11111111111111111111000100001110 $
1'
#87
0'
#88
b11111111111111111111100010000111 $
1'
#89
0'
#90
b11111111111111111111110001000011 $
1'
1)
#91
0'
#92
b11111111111111111111111000100001 $
1'
#93
0'
#94
b11111111111111111111111100010000 $
1'
#95
0'
#96
b11111111111111111111111110001000 $
1'
0)
#97
0'
#98
b11111111111111111111111111000100 $
1'
#99
0'
